LICENSE
MANIFEST.in
README.md
setup.cfg
setup.py
unit_convert.py
unit_convert.egg-info/PKG-INFO
unit_convert.egg-info/SOURCES.txt
unit_convert.egg-info/dependency_links.txt
unit_convert.egg-info/top_level.txt