Metadata-Version: 2.1
Name: unit-convert
Version: 1.1.0
Summary: Easy way of converting units.
Home-page: https://github.com/huntfx/unit-convert
Download-URL: https://github.com/huntfx/unit-convert/archive/1.1.0.tar.gz
Author: Peter Hunt
Author-email: peterh@blue-zoo.co.uk
License: MIT
Project-URL: Source, https://github.com/huntfx/unit-convert
Project-URL: Issues, https://github.com/huntfx/unit-convert/issues
Keywords: unit,convert,conversion
Classifier: Development Status :: 4 - Beta
Classifier: Intended Audience :: Developers
Classifier: License :: OSI Approved :: MIT License
Classifier: Programming Language :: Python
Classifier: Programming Language :: Python :: 2
Classifier: Programming Language :: Python :: 2.7
Classifier: Programming Language :: Python :: 3
Classifier: Programming Language :: Python :: 3.4
Classifier: Programming Language :: Python :: 3.5
Classifier: Programming Language :: Python :: 3.6
Classifier: Programming Language :: Python :: 3.7
Classifier: Programming Language :: Python :: 3.8
Requires-Python: >=2.5
License-File: LICENSE
